{
    "ID": 113,
    "post_author": "0",
    "post_date": "2023-03-22 15:55:44",
    "post_date_gmt": "2023-03-22 15:55:44",
    "post_content": "<button class=\"comp-update-btn\"><a href=\"https:\/\/dev2.biocensus.co.uk\/staff-info-update\/?frm_action=edit&entry=[id]\">Update Staff Info Entry<\/a><\/button>",
    "post_title": "Staff Info Update Button View 2",
    "post_excerpt": "",
    "post_status": "private",
    "comment_status": "closed",
    "ping_status": "closed",
    "post_password": "",
    "post_name": "staff-info-update-button-view-2",
    "to_ping": "",
    "pinged": "",
    "post_modified": "2025-07-25 14:00:44",
    "post_modified_gmt": "2025-07-25 14:00:44",
    "post_content_filtered": "",
    "post_parent": 0,
    "guid": "https:\/\/test1.biocensus.co.uk\/frm_display\/staff-info-update-button-view-2\/",
    "menu_order": 0,
    "post_type": "frm_display",
    "post_mime_type": "",
    "comment_count": "0",
    "filter": "raw",
    "form_key": "tj0g6",
    "meta": {
        "frm_form_id": [
            "42"
        ],
        "frm_show_count": [
            "all"
        ],
        "frm_options": [
            "a:21:{s:13:\"date_field_id\";s:0:\"\";s:14:\"edate_field_id\";s:0:\"\";s:21:\"repeat_event_field_id\";s:0:\"\";s:21:\"repeat_edate_field_id\";s:0:\"\";s:14:\"before_content\";s:0:\"\";s:13:\"after_content\";s:0:\"\";s:9:\"empty_msg\";s:0:\"\";s:5:\"limit\";s:0:\"\";s:9:\"page_size\";s:0:\"\";s:5:\"no_rt\";i:0;s:15:\"ajax_pagination\";s:1:\"0\";s:5:\"where\";a:1:{i:0;i:560;}s:8:\"where_is\";a:1:{i:0;s:1:\"=\";}s:9:\"where_val\";a:1:{i:0;s:12:\"current_user\";}s:8:\"where_or\";a:1:{i:0;i:0;}s:11:\"where_group\";a:1:{i:0;i:0;}s:14:\"where_group_or\";a:1:{i:0;i:0;}s:8:\"filename\";s:0:\"\";s:16:\"export_link_text\";s:13:\"Export to CSV\";s:18:\"export_with_params\";s:1:\"0\";s:20:\"view_export_possible\";i:0;}"
        ],
        "frm_param": [
            "entry"
        ],
        "frm_dyncontent": [
            ""
        ],
        "frm_type": [
            "id"
        ],
        "frm_active_preview_filter": [
            "limited"
        ],
        "view_uuid": [
            "10ced2e1-c9cf-4af6-8351-d3882a89556c"
        ],
        "frm_view_type": [
            "classic"
        ]
    },
    "layout": null
}